pynlpl/__init__.py
pynlpl/local/__init__.py
pynlpl/local/audio.py
pynlpl/local/text/nltk.py
pynlpl/local/text/spacy.py
pynlpl/local/text/stanza.py
pynlpl/web/__init__.py
pynlpl/web/audio.py
pynlpl/web/text.py
pynlp_lib-0.1.4.dist-info/LICENSE
pynlp_lib-0.1.4.dist-info/METADATA
pynlp_lib-0.1.4.dist-info/WHEEL
pynlp_lib-0.1.4.dist-info/top_level.txt
pynlp_lib-0.1.4.dist-info/RECORD
