Metadata-Version: 2.1
Name: pynlp-lib
Version: 0.1.4
Summary: PyNLP Lib is an open source Python NLP library that provides functionality for both web and local development
Author-email: Yujian Tang <yujian@thetextapi.com>
License: MIT License        
Project-URL: Homepage, https://github.com/The-Text-API/pynlp-lib
Project-URL: Bug Tracker, https://github.com/The-Text-API/pynlp-lib/issues
Classifier: Programming Language :: Python :: 3
Classifier: License :: OSI Approved :: MIT License
Classifier: Operating System :: OS Independent
Requires-Python: >=3.8
License-File: LICENSE
